images/nb-clean.png
nb_clean/__init__.py
nb_clean/__main__.py
nb_clean/cli.py
nb_clean-4.0.0.dist-info/LICENSE
nb_clean-4.0.0.dist-info/METADATA
nb_clean-4.0.0.dist-info/WHEEL
nb_clean-4.0.0.dist-info/entry_points.txt
nb_clean-4.0.0.dist-info/RECORD
