Metadata-Version: 2.1
Name: nb-clean
Version: 4.0.0
Summary: Clean Jupyter notebooks for versioning
Home-page: https://github.com/srstevenson/nb-clean
License: ISC
Keywords: jupyter,notebook,clean,filter,git
Author: Scott Stevenson
Author-email: scott@stevenson.io
Requires-Python: >=3.9,<4.0
Classifier: Development Status :: 5 - Production/Stable
Classifier: Intended Audience :: Science/Research
Classifier: License :: OSI Approved
Classifier: Natural Language :: English
Classifier: Programming Language :: Python :: 3
Classifier: Programming Language :: Python :: 3.9
Classifier: Programming Language :: Python :: 3.10
Classifier: Programming Language :: Python :: 3.11
Classifier: Programming Language :: Python :: 3.12
Classifier: Programming Language :: Python :: 3.13
Requires-Dist: nbformat (>=5.9.2)
Project-URL: Repository, https://github.com/srstevenson/nb-clean
